fastapi_init/__init__.py
fastapi_init/main.py
fastapi_init-0.1.12.dist-info/METADATA
fastapi_init-0.1.12.dist-info/WHEEL
fastapi_init-0.1.12.dist-info/entry_points.txt
fastapi_init-0.1.12.dist-info/top_level.txt
fastapi_init-0.1.12.dist-info/RECORD
