Metadata-Version: 2.1
Name: fastapi-init
Version: 0.1.12
Summary: A simple Python library
Author: Le Dinh Manh
Author-email: manhld@rabiloo.com
Requires-Python: >=3.6
Requires-Dist: requests
Requires-Dist: GitPython
